{
  "type": "FeatureCollection",
  "features": [
    {
      "type": "Feature",
      "geometry": {
        "type": "Point",
        "coordinates": [
          57.4796456,
          -20.2463908
        ]
      },
      "properties": {
        "id": 510587886,
        "name": "Belle Rose EV Charging",
        "amenity": "charging_station"
      }
    }
  ]
}